{
    "frame_shape": [
        564, 
        474
    ],
    "scale": 5.35,
    "areas": [
        {
            "name": "Arm_1",
            "center": [
                266,
                360
            ],
            "width": 80,
            "height": 220,
            "angle": 0
        },
        {
            "name": "Arm_2",
            "center": [
                120,
                100
            ],
            "width": 80,
            "height": 220,
            "angle": -60
        },
        {
            "name": "Arm_3",
            "center": [
                429,
                105
            ],
            "width": 80,
            "height": 220,
            "angle": 60
        }
    ],
    "points": []
}